odoo/addons/maintenance_security/README.rst
odoo/addons/maintenance_security/__init__.py
odoo/addons/maintenance_security/__manifest__.py
odoo/addons/maintenance_security/i18n/es.po
odoo/addons/maintenance_security/i18n/it.po
odoo/addons/maintenance_security/i18n/maintenance_security.pot
odoo/addons/maintenance_security/models/__init__.py
odoo/addons/maintenance_security/models/mail_followers.py
odoo/addons/maintenance_security/readme/CONTRIBUTORS.md
odoo/addons/maintenance_security/readme/DESCRIPTION.md
odoo/addons/maintenance_security/static/description/icon.png
odoo/addons/maintenance_security/static/description/index.html
odoo/addons/maintenance_security/tests/__init__.py
odoo/addons/maintenance_security/tests/test_maintenance_security.py
odoo/addons/maintenance_security/views/maintenance_views.xml
odoo_addon_maintenance_security-18.0.2.0.0.dist-info/METADATA
odoo_addon_maintenance_security-18.0.2.0.0.dist-info/WHEEL
odoo_addon_maintenance_security-18.0.2.0.0.dist-info/top_level.txt
odoo_addon_maintenance_security-18.0.2.0.0.dist-info/RECORD
